Workbook

Sheet SUMMARY
C1: SCOPE : | D1: ='BASE BID'!D1 -> Plumbing
C2: PROJECT LOCATION : | D2: ='BASE BID'!D2 -> Lewisville Resturant, 2000 FM 544, Lewisvilee TX 75056
C3: DATE SUBMITTED : | D3: ='BASE BID'!D3 -> 46071
C4: PROJECT TYPE: | D4: ='BASE BID'!D4 -> Commercial
C5: REVISION NO.: | D5: ='BASE BID'!D5 -> 00
A7: ITEM # | B7: CSI DIV. | C7: DESCRIPTION | M7: TOTAL LABOR COST | N7: TOTAL MATERIAL COST | O7: TRADE COST
A8: =IF(G8<>"",1+MAX(#REF!),"") | B8: =VLOOKUP($C8,$C$38:$D$61,2,0) -> 01 00 | C8: GENERAL REQUIREMENTS | M8: =SUM('BASE BID'!K10:K16) -> 15000 | N8: =SUM('BASE BID'!M10:M16) -> 0 | O8: =M8+N8 -> 15000
B9: =VLOOKUP($C9,$C$38:$D$61,2,0) -> 22 00 | C9: PLUMBING | M9: =SUM('BASE BID'!K21:K133) -> 48735.792 | N9: =SUM('BASE BID'!M135) -> 110451.78 | O9: =M9+N9 -> 159187.58
A10: SUB TOTAL | M10: =SUM(M8:M9) -> 63735.792 | N10: =SUM(N8:N9) -> 110451.78 | O10: =SUM(O8:O9) -> 174187.58
A11: MATERIAL TAX | D11: 0.0825 | M11: 0 | N11: =D11*N10 -> 9112.2722 | O11: =M11+N11 -> 9112.2722
A12: OVERHEAD & PROFIT / INFLATION (Material) | D12: 0.1 | M12: 0 | N12: =D12*N10 -> 11045.178 | O12: =M12+N12 -> 11045.178
A13: OVERHEAD & PROFIT (Labor) | D13: 0.15 | M13: =M10*D13 -> 9560.3688 | N13: 0 | O13: =M13+N13 -> 9560.3688
A14: CASH ALLOWANCE | M14: 0 | N14: 0 | O14: 0
A15: BOND FEE | D15: 0.015 | O15: =D15*SUM(O10:O14) -> 3058.5809
A16: TOTAL BASE BID | O16: =SUM(O10:O15) -> 206963.98
B18: Note
A19: 1 | C19: Riser Pipe Diagram not given scale so we assumed the scale.
A20: 2 | C20: Lochinvar Sled Furnished By owner PC Responsible For Plumbing Connection To Sled Including Boiler Venting, Boiler Gas Connection Boiler Condensate Drainage, Boiler System Domestic Cold Water Connection And Domestic Hot Water
A21: 3
M23: Legend
M24: DIV. = Division
M25: F.C = Waste or diff. factor
M26: D.O. = Daily Output
B27: Exclusions | M27: LBR. HR. = Labor Hours
A28: 1 | C28: Union Wages. | M28: SF = Square Feet
A29: 2 | C29: Any work not mentioned above. | M29: LF = Linear Feet
A30: 3 | C30: Building Charges (if any). | M30: EA = Each
A31: 4 | C31: Security fee (if any). | M31: CY = Cubic Yard
M32: SY = Fquare Yard
M33: loc = location
M34: LS = lump sum
M35: LBS = Pounds
C38: GENERAL REQUIREMENTS | D38: 01 00
C39: SITE CONDITIONS | D39: 02 00
C40: CONCRETE | D40: 03 00
C41: MASONRY | D41: 04 00
C42: METAL | D42: 05 00
C43: WOOD, PLASTICS & COMPOSITES | D43: 06 00
C44: WATERPROOFING | D44: 07 00
C45: OPENNINGS | D45: 08 00
C46: FINISHES | D46: 09 00
C47: SPECIALITES | D47: 10 00
C48: EQUIPMENT | D48: 11 00
C49: FURNISHINGS | D49: 12 00
... C61: UTILITIES | D61: 33 00

Sheet BASE BID
C1: SCOPE : | D1: Plumbing
C2: PROJECT LOCATION : | D2: Lewisville Resturant, 2000 FM 544, Lewisvilee TX 75056
C3: DATE SUBMITTED : | D3: 46071
C4: PROJECT TYPE: | D4: Commercial
C5: REVISION NO.: | D5: 00
A7: ITEM # | B7: CSI DIV. | C7: DESCRIPTION | D7: BARE QTY. | E7: WASTAGE | F7: QTY. WITH WASTAGE | G7: UNIT | H7: UNIT LABOR HOURS | I7: TOTAL LABOR HOURS | J7: PER HOUR LABOR RATE | K7: TOTAL LABOR COST | L7: UNIT MATERIAL COST | M7: TOTAL MATERIAL COST | N7: ITEM COST | O7: TRADE COST
A8: =IF(G8<>"",1+MAX(#REF!),"") | B8: =VLOOKUP($C8,$C$139:$D$162,2,0) -> 01 00 | C8: GENERAL REQUIREMENTS | O8: =SUM(N9:N17) -> 15000 | P8: =SUM(N20:N134) -> 159187.58
A10: =IF(G10<>"",1+MAX($A$8:A9),"") -> 1 | C10: Plan Design & Permitting | D10: 1 | E10: 0 | F10: =CEILING(SUM(D10:D10)*(1+E10),1) -> 1 | G10: LS | H10: 0 | I10: =F10*H10 -> 0 | J10: 0 | K10: 1700 | M10: =L10*F10 -> 0 | N10: 1700 | P10: 0.0085
A11: =IF(G11<>"",1+MAX($A$8:A10),"") -> 2 | C11: Utilities | D11: 1 | E11: 0 | F11: =CEILING(SUM(D11:D11)*(1+E11),1) -> 1 | G11: LS | H11: 0 | I11: =F11*H11 -> 0 | J11: 0 | K11: 2500 | M11: =L11*F11 -> 0 | N11: 2500 | P11: 0.0075
A12: =IF(G12<>"",1+MAX($A$8:A11),"") -> 3 | C12: Equipment & Tools | D12: 1 | E12: 0 | F12: =CEILING(SUM(D12:D12)*(1+E12),1) -> 1 | G12: LS | H12: 0 | I12: =F12*H12 -> 0 | J12: 0 | K12: 4500 | M12: =L12*F12 -> 0 | N12: 4500 | P12: 0.0095
A13: =IF(G13<>"",1+MAX($A$8:A12),"") -> 4 | C13: Signage & Promotion | D13: 1 | E13: 0 | F13: =CEILING(SUM(D13:D13)*(1+E13),1) -> 1 | G13: LS | H13: 0 | I13: =F13*H13 -> 0 | J13: 0 | K13: 0 | M13: =L13*F13 -> 0 | N13: =K13*F13 -> 0 | P13: 0.0065
A14: =IF(G14<>"",1+MAX($A$8:A13),"") -> 5 | C14: Cleaning & Final | D14: 1 | E14: 0 | F14: =CEILING(SUM(D14:D14)*(1+E14),1) -> 1 | G14: LS | H14: 0 | I14: =F14*H14 -> 0 | J14: 0 | K14: 0 | M14: =L14*F14 -> 0 | N14: =K14*F14 -> 0 | P14: 0.0075
A15: =IF(G15<>"",1+MAX($A$8:A14),"") -> 6 | C15: Bonds, Insurance, Legal | D15: 1 | E15: 0 | F15: =CEILING(SUM(D15:D15)*(1+E15),1) -> 1 | G15: LS | H15: 0 | I15: =F15*H15 -> 0 | J15: 0 | K15: 2800 | M15: =L15*F15 -> 0 | N15: 2800 | P15: 0.015
A16: =IF(G16<>"",1+MAX($A$8:A15),"") -> 7 | C16: Project Management & Supervision | D16: 1 | E16: 0 | F16: =CEILING(SUM(D16:D16)*(1+E16),1) -> 1 | G16: LS | H16: 0 | I16: =F16*H16 -> 0 | J16: 0 | K16: 3500 | M16: =L16*F16 -> 0 | N16: 3500 | P16: 0.035
A17: =IF(G17<>"",1+MAX($A$8:A16),"")
A18: =IF(G18<>"",1+MAX($A$8:A17),"") | B18: =SUMMARY!B9 -> 22 00 | C18: PLUMBING | O18: =SUM(N19:N134) -> 159187.58
A19: =IF(G19<>"",1+MAX($A$8:A18),"")
A20: =IF(G20<>"",1+MAX($A$8:A19),"") | C20: Pipework
A21: =IF(G21<>"",1+MAX($A$8:A20),"") -> 8 | C21: (3" Dia) Vent Pipe | D21: 33.74 | E21: 0.05 | F21: =CEILING(SUM(D21:D21)*(1+E21),1) -> 36 | G21: LF | H21: 0.305 | I21: =H21*F21 -> 10.98 | J21: 48 | K21: =J21*I21 -> 527.04 | L21: 16.25 | M21: =L21*F21 -> 585 | N21: =M21+K21 -> 1112.04
A22: =IF(G22<>"",1+MAX($A$8:A21),"") -> 9 | C22: (2" Dia) Vent Pipe | D22: 484.33 | E22: 0.05 | F22: =CEILING(SUM(D22:D22)*(1+E22),1) -> 509 | G22: LF | H22: 0.25 | I22: =H22*F22 -> 127.25 | J22: 48 | K22: =J22*I22 -> 6108 | L22: 9.15 | M22: =L22*F22 -> 4657.35 | N22: =M22+K22 -> 10765.35
A23: =IF(G23<>"",1+MAX($A$8:A22),"") -> 10 | C23: (5" Dia) Strom Drain Pipe | D23: 153.37 | E23: 0.05 | F23: =CEILING(SUM(D23:D23)*(1+E23),1) -> 162 | G23: LF | H23: 0.45 | I23: =H23*F23 -> 72.9 | J23: 48 | K23: =J23*I23 -> 3499.2 | L23: 26 | M23: =L23*F23 -> 4212 | N23: =M23+K23 -> 7711.2
A24: =IF(G24<>"",1+MAX($A$8:A23),"") -> 11 | C24: (4" Dia) Grease Waste Pipe | D24: 93.69 | E24: 0.05 | F24: =CEILING(SUM(D24:D24)*(1+E24),1) -> 99 | G24: LF | H24: 0.41 | I24: =H24*F24 -> 40.59 | J24: 48 | K24: =J24*I24 -> 1948.32 | L24: 21.5 | M24: =L24*F24 -> 2128.5 | N24: =M24+K24 -> 4076.82
A25: =IF(G25<>"",1+MAX($A$8:A24),"") -> 12 | C25: (3" Dia) Grease Waste Pipe | D25: 217.93 | E25: 0.05 | F25: =CEILING(SUM(D25:D25)*(1+E25),1) -> 229 | G25: LF | H25: 0.305 | I25: =H25*F25 -> 69.845 | J25: 48 | K25: =J25*I25 -> 3352.56 | L25: 16.25 | M25: =L25*F25 -> 3721.25 | N25: =M25+K25 -> 7073.81
A26: =IF(G26<>"",1+MAX($A$8:A25),"") -> 13 | C26: (2" Dia) Grease Waste Pipe | D26: 10.18 | E26: 0.05 | F26: =CEILING(SUM(D26:D26)*(1+E26),1) -> 11 | G26: LF | H26: 0.25 | I26: =H26*F26 -> 2.75 | J26: 48 | K26: =J26*I26 -> 132 | L26: 9.15 | M26: =L26*F26 -> 100.65 | N26: =M26+K26 -> 232.65
A27: =IF(G27<>"",1+MAX($A$8:A26),"") -> 14 | C27: (4" Dia) Sanitary Waste Pipe | D27: 60.63 | E27: 0.05 | F27: =CEILING(SUM(D27:D27)*(1+E27),1) -> 64 | G27: LF | H27: 0.33 | I27: =H27*F27 -> 21.12 | J27: 48 | K27: =J27*I27 -> 1013.76 | L27: 21.5 | M27: =L27*F27 -> 1376 | N27: =M27+K27 -> 2389.76
A28: =IF(G28<>"",1+MAX($A$8:A27),"") -> 15 | C28: (3" Dia) Sanitary Waste Pipe | D28: 191.41 | E28: 0.05 | F28: =CEILING(SUM(D28:D28)*(1+E28),1) -> 201 | G28: LF | H28: 0.305 | I28: =H28*F28 -> 61.305 | J28: 48 | K28: =J28*I28 -> 2942.64 | L28: 16.25 | M28: =L28*F28 -> 3266.25 | N28: =M28+K28 -> 6208.89
A29: =IF(G29<>"",1+MAX($A$8:A28),"") -> 16 | C29: (2" Dia) Sanitary Waste Pipe | D29: 69.01 | E29: 0.05 | F29: =CEILING(SUM(D29:D29)*(1+E29),1) -> 73 | G29: LF | H29: 0.25 | I29: =H29*F29 -> 18.25 | J29: 48 | K29: =J29*I29 -> 876 | L29: 9.15 | M29: =L29*F29 -> 667.95 | N29: =M29+K29 -> 1543.95
A30: =IF(G30<>"",1+MAX($A$8:A29),"") -> 17 | C30: (6" Dia) Fire Water Service Pipe | D30: 21.8 | E30: 0.05 | F30: =CEILING(SUM(D30:D30)*(1+E30),1) -> 23 | G30: LF | H30: 0.41 | I30: =H30*F30 -> 9.43 | J30: 48 | K30: =J30*I30 -> 452.64 | L30: 46 | M30: =L30*F30 -> 1058 | N30: =M30+K30 -> 1510.64
A31: =IF(G31<>"",1+MAX($A$8:A30),"") -> 18 | C31: (2" Dia) Cold Water Pipe | D31: 35.77 | E31: 0.05 | F31: =CEILING(SUM(D31:D31)*(1+E31),1) -> 38 | G31: LF | H31: 0.25 | I31: =H31*F31 -> 9.5 | J31: 48 | K31: =J31*I31 -> 456 | L31: 9.15 | M31: =L31*F31 -> 347.7 | N31: =M31+K31 -> 803.7
A32: =IF(G32<>"",1+MAX($A$8:A31),"") -> 19 | C32: (1 1/2" Dia) Cold Water Pipe | D32: 82.23 | E32: 0.05 | F32: =CEILING(SUM(D32:D32)*(1+E32),1) -> 87 | G32: LF | H32: 0.18 | I32: =H32*F32 -> 15.66 | J32: 48 | K32: =J32*I32 -> 751.68 | L32: 8.6 | M32: =L32*F32 -> 748.2 | N32: =M32+K32 -> 1499.88
... A48: =IF(G48<>"",1+MAX($A$8:A47),"") -> 35 | C48: (1 1/2" Dia) Natural Gas Pipe | D48: 84.05 | E48: 0.05 | F48: =CEILING(SUM(D48:D48)*(1+E48),1) -> 89 | G48: LF | H48: 0.18 | I48: =H48*F48 -> 16.02 | J48: 48 | K48: =J48*I48 -> 768.96 | L48: 8.6 | M48: =L48*F48 -> 765.4 | N48: =M48+K48 -> 1534.36
A49: =IF(G49<>"",1+MAX($A$8:A48),"")
A50: =IF(G50<>"",1+MAX($A$8:A49),"") | C50: Pipe Insulation
A51: =IF(G51<>"",1+MAX($A$8:A50),"") -> 36 | C51: Pipe Insulation (Assume) | D51: 2502 | E51: 0.05 | F51: =CEILING(SUM(D51:D51)*(1+E51),1) -> 2628 | G51: LF | H51: 0.028 | I51: =H51*F51 -> 73.584 | J51: 48 | K51: =J51*I51 -> 3532.032 | L51: 2.58 | M51: =L51*F51 -> 6780.24 | N51: =M51+K51 -> 10312.272
A52: =IF(G52<>"",1+MAX($A$8:A51),"")
A53: =IF(G53<>"",1+MAX($A$8:A52),"")
A54: =IF(G54<>"",1+MAX($A$8:A53),"") | C54: Fitting
A55: =IF(G55<>"",1+MAX($A$8:A54),"") -> 37 | C55: (1" Dia) 90 Degree Elbow | D55: 4 | E55: 0 | F55: =CEILING(SUM(D55:D55)*(1+E55),1) -> 4 | G55: EA | H55: 0.8 | I55: =H55*F55 -> 3.2 | J55: 48 | K55: =J55*I55 -> 153.6 | L55: 22 | M55: =L55*F55 -> 88 | N55: =M55+K55 -> 241.6
A56: =IF(G56<>"",1+MAX($A$8:A55),"") -> 38 | C56: (2" Dia) 90 Degree Elbow | D56: 6 | E56: 0 | F56: =CEILING(SUM(D56:D56)*(1+E56),1) -> 6 | G56: EA | H56: 0.8 | I56: =H56*F56 -> 4.8 | J56: 48 | K56: =J56*I56 -> 230.4 | L56: 22 | M56: =L56*F56 -> 132 | N56: =M56+K56 -> 362.4
A57: =IF(G57<>"",1+MAX($A$8:A56),"") -> 39 | C57: (2" Dia) 45 Degree Elbow | D57: 2 | E57: 0 | F57: =CEILING(SUM(D57:D57)*(1+E57),1) -> 2 | G57: EA | H57: 0.8 | I57: =H57*F57 -> 1.6 | J57: 48 | K57: =J57*I57 -> 76.8 | L57: 22 | M57: =L57*F57 -> 44 | N57: =M57+K57 -> 120.8
A58: =IF(G58<>"",1+MAX($A$8:A57),"") -> 40 | C58: (3" Dia) 45 Degree Elbow | D58: 6 | E58: 0 | F58: =CEILING(SUM(D58:D58)*(1+E58),1) -> 6 | G58: EA | H58: 0.8 | I58: =H58*F58 -> 4.8 | J58: 48 | K58: =J58*I58 -> 230.4 | L58: 22 | M58: =L58*F58 -> 132 | N58: =M58+K58 -> 362.4
A59: =IF(G59<>"",1+MAX($A$8:A58),"") -> 41 | C59: (3" Dia) 90 Degree Elbow | D59: 2 | E59: 0 | F59: =CEILING(SUM(D59:D59)*(1+E59),1) -> 2 | G59: EA | H59: 0.8 | I59: =H59*F59 -> 1.6 | J59: 48 | K59: =J59*I59 -> 76.8 | L59: 22 | M59: =L59*F59 -> 44 | N59: =M59+K59 -> 120.8
A60: =IF(G60<>"",1+MAX($A$8:A59),"") -> 42 | C60: (4" Dia) 45 Degree Elbow | D60: 4 | E60: 0 | F60: =CEILING(SUM(D60:D60)*(1+E60),1) -> 4 | G60: EA | H60: 0.8 | I60: =H60*F60 -> 3.2 | J60: 48 | K60: =J60*I60 -> 153.6 | L60: 22 | M60: =L60*F60 -> 88 | N60: =M60+K60 -> 241.6
A61: =IF(G61<>"",1+MAX($A$8:A60),"") -> 43 | C61: (5" Dia) 90 Degree Elbow | D61: 2 | E61: 0 | F61: =CEILING(SUM(D61:D61)*(1+E61),1) -> 2 | G61: EA | H61: 0.8 | I61: =H61*F61 -> 1.6 | J61: 48 | K61: =J61*I61 -> 76.8 | L61: 22 | M61: =L61*F61 -> 44 | N61: =M61+K61 -> 120.8
A62: =IF(G62<>"",1+MAX($A$8:A61),"") -> 44 | C62: (5" Dia) 45 Degree Elbow | D62: 1 | E62: 0 | F62: =CEILING(SUM(D62:D62)*(1+E62),1) -> 1 | G62: EA | H62: 0.8 | I62: =H62*F62 -> 0.8 | J62: 48 | K62: =J62*I62 -> 38.4 | L62: 22 | M62: =L62*F62 -> 22 | N62: =M62+K62 -> 60.4
A63: =IF(G63<>"",1+MAX($A$8:A62),"") -> 45 | C63: (1/2" Dia) 90 Degree Elbow | D63: 5 | E63: 0 | F63: =CEILING(SUM(D63:D63)*(1+E63),1) -> 5 | G63: EA | H63: 0.8 | I63: =H63*F63 -> 4 | J63: 48 | K63: =J63*I63 -> 192 | L63: 22 | M63: =L63*F63 -> 110 | N63: =M63+K63 -> 302
A64: =IF(G64<>"",1+MAX($A$8:A63),"") -> 46 | C64: (3/4" Dia) 90 Degree Elbow | D64: 13 | E64: 0 | F64: =CEILING(SUM(D64:D64)*(1+E64),1) -> 13 | G64: EA | H64: 0.8 | I64: =H64*F64 -> 10.4 | J64: 48 | K64: =J64*I64 -> 499.2 | L64: 22 | M64: =L64*F64 -> 286 | N64: =M64+K64 -> 785.2
A65: =IF(G65<>"",1+MAX($A$8:A64),"") -> 47 | C65: (1 1/2" Dia) 90 Degree Elbow | D65: 6 | E65: 0 | F65: =CEILING(SUM(D65:D65)*(1+E65),1) -> 6 | G65: EA | H65: 0.8 | I65: =H65*F65 -> 4.8 | J65: 48 | K65: =J65*I65 -> 230.4 | L65: 22 | M65: =L65*F65 -> 132 | N65: =M65+K65 -> 362.4
A66: =IF(G66<>"",1+MAX($A$8:A65),"") -> 48 | C66: (1 1/4" Dia) 90 Degree Elbow | D66: 6 | E66: 0 | F66: =CEILING(SUM(D66:D66)*(1+E66),1) -> 6 | G66: EA | H66: 0.8 | I66: =H66*F66 -> 4.8 | J66: 48 | K66: =J66*I66 -> 230.4 | L66: 22 | M66: =L66*F66 -> 132 | N66: =M66+K66 -> 362.4
... A100: =IF(G100<>"",1+MAX($A$8:A99),"") -> 82 | C100: (2 1/2"x1 1/2"x2 1/2") Tee | D100: 1 | E100: 0 | F100: =CEILING(SUM(D100:D100)*(1+E100),1) -> 1 | G100: EA | H100: 1.1 | I100: =H100*F100 -> 1.1 | J100: 48 | K100: =J100*I100 -> 52.8 | L100: 44 | M100: =L100*F100 -> 44 | N100: =M100+K100 -> 96.8
A101: =IF(G101<>"",1+MAX($A$8:A100),"")
A102: =IF(G102<>"",1+MAX($A$8:A101),"") | C102: Fixture
A103: =IF(G103<>"",1+MAX($A$8:A102),"") -> 83 | C103: WC-1: Water Closet Mfg: American Standard Model: 3043.001 | D103: 2 | E103: 0 | F103: =CEILING(SUM(D103:D103)*(1+E103),1) -> 2 | G103: EA | H103: 3.5 | I103: =H103*F103 -> 7 | J103: 48 | K103: =J103*I103 -> 336 | L103: 538.45 | M103: =L103*F103 -> 1076.9 | N103: =M103+K103 -> 1412.9
A104: =IF(G104<>"",1+MAX($A$8:A103),"") -> 84 | C104: WC-2: Water Closet Mfg: American Standard Model: 3043.001 | D104: 1 | E104: 0 | F104: =CEILING(SUM(D104:D104)*(1+E104),1) -> 1 | G104: EA | H104: 3.5 | I104: =H104*F104 -> 3.5 | J104: 48 | K104: =J104*I104 -> 168 | L104: 538.45 | M104: =L104*F104 -> 538.45 | N104: =M104+K104 -> 706.45
A105: =IF(G105<>"",1+MAX($A$8:A104),"") -> 85 | C105: LAV-1: Lavatory Mfg: American Standard Model: 0495.221 | D105: 4 | E105: 0 | F105: =CEILING(SUM(D105:D105)*(1+E105),1) -> 4 | G105: EA | H105: 3.2 | I105: =H105*F105 -> 12.8 | J105: 48 | K105: =J105*I105 -> 614.4 | L105: 110 | M105: =L105*F105 -> 440 | N105: =M105+K105 -> 1054.4
A106: =IF(G106<>"",1+MAX($A$8:A105),"") -> 86 | C106: UR-1: Urinal Mfg: American Standard Model: 6590.001 | D106: 1 | E106: 0 | F106: =CEILING(SUM(D106:D106)*(1+E106),1) -> 1 | G106: EA | H106: 2.65 | I106: =H106*F106 -> 2.65 | J106: 48 | K106: =J106*I106 -> 127.2 | L106: 415 | M106: =L106*F106 -> 415 | N106: =M106+K106 -> 542.2
A107: =IF(G107<>"",1+MAX($A$8:A106),"") -> 87 | C107: MS-1: Mop Sink Mfg: Stern-Williams Model: SSBC-1500 | D107: 1 | E107: 0 | F107: =CEILING(SUM(D107:D107)*(1+E107),1) -> 1 | G107: EA | H107: 2.5 | I107: =H107*F107 -> 2.5 | J107: 48 | K107: =J107*I107 -> 120 | L107: 659 | M107: =L107*F107 -> 659 | N107: =M107+K107 -> 779
A108: =IF(G108<>"",1+MAX($A$8:A107),"") -> 88 | C108: KS-1: 3 Compartment Kitchen Sink Mfg: Provided by Food Service Equipment Vendor | D108: 1 | E108: 0 | F108: =CEILING(SUM(D108:D108)*(1+E108),1) -> 1 | G108: EA | H108: 3.2 | I108: =H108*F108 -> 3.2 | J108: 48 | K108: =J108*I108 -> 153.6 | L108: 1200 | M108: =L108*F108 -> 1200 | N108: =M108+K108 -> 1353.6
A109: =IF(G109<>"",1+MAX($A$8:A108),"") -> 89 | C109: KS-2: Single Compartment Kitchen Sink Mfg: Provided by Food Service Equipment Vendor | D109: 2 | E109: 0 | F109: =CEILING(SUM(D109:D109)*(1+E109),1) -> 2 | G109: EA | H109: 2.85 | I109: =H109*F109 -> 5.7 | J109: 48 | K109: =J109*I109 -> 273.6 | L109: 588 | M109: =L109*F109 -> 1176 | N109: =M109+K109 -> 1449.6
A110: =IF(G110<>"",1+MAX($A$8:A109),"") -> 90 | C110: FS-1: Floor Sink Mfg: Jay R. Smith Model: 3151T-13 | D110: 8 | E110: 0 | F110: =CEILING(SUM(D110:D110)*(1+E110),1) -> 8 | G110: EA | H110: 3.5 | I110: =H110*F110 -> 28 | J110: 48 | K110: =J110*I110 -> 1344 | L110: 1234.378 | M110: =L110*F110 -> 9875.024 | N110: =M110+K110 -> 11219.024
A111: =IF(G111<>"",1+MAX($A$8:A110),"") -> 91 | C111: FS-2: Floor Sink Mfg: Advance Tabco Model: FD-3612 | D111: 5 | E111: 0 | F111: =CEILING(SUM(D111:D111)*(1+E111),1) -> 5 | G111: EA | H111: 2.85 | I111: =H111*F111 -> 14.25 | J111: 48 | K111: =J111*I111 -> 684 | L111: 1055 | M111: =L111*F111 -> 5275 | N111: =M111+K111 -> 5959
A112: =IF(G112<>"",1+MAX($A$8:A111),"") -> 92 | C112: HS-1: Single Compartment Hand Washing Sink Mfg: Advance Tabco Model: 7-PS-63 | D112: 7 | E112: 0 | F112: =CEILING(SUM(D112:D112)*(1+E112),1) -> 7 | G112: EA | H112: 4 | I112: =H112*F112 -> 28 | J112: 48 | K112: =J112*I112 -> 1344 | L112: 2416 | M112: =L112*F112 -> 16912 | N112: =M112+K112 -> 18256
A113: =IF(G113<>"",1+MAX($A$8:A112),"") -> 93 | C113: FD-1: Floor Drain Mfg: Jay R. Smith Model: 2005-NB | D113: 2 | E113: 0 | F113: =CEILING(SUM(D113:D113)*(1+E113),1) -> 2 | G113: EA | H113: 1.25 | I113: =H113*F113 -> 2.5 | J113: 48 | K113: =J113*I113 -> 120 | L113: 137.91 | M113: =L113*F113 -> 275.82 | N113: =M113+K113 -> 395.82
A114: =IF(G114<>"",1+MAX($A$8:A113),"") -> 94 | C114: FD-2: Floor Drain Mfg: Jay R. Smith Model: 2005-NB (with 4" Funnel Drain) | D114: 1 | E114: 0 | F114: =CEILING(SUM(D114:D114)*(1+E114),1) -> 1 | G114: EA | H114: 1.25 | I114: =H114*F114 -> 1.25 | J114: 48 | K114: =J114*I114 -> 60 | L114: 137.91 | M114: =L114*F114 -> 137.91 | N114: =M114+K114 -> 197.91
... A117: =IF(G117<>"",1+MAX($A$8:A116),"") -> 97 | C117: FCO - Floor Cleanout - Details Not Provided | D117: 4 | E117: 0 | F117: =CEILING(SUM(D117:D117)*(1+E117),1) -> 4 | G117: EA | H117: 1.25 | I117: =H117*F117 -> 5 | J117: 48 | K117: =J117*I117 -> 240 | L117: 110 | M117: =L117*F117 -> 440 | N117: =M117+K117 -> 680
A118: =IF(G118<>"",1+MAX($A$8:A117),"")
A119: =IF(G119<>"",1+MAX($A$8:A118),"") | C119: Pump
A120: =IF(G120<>"",1+MAX($A$8:A119),"") -> 98 | C120: RCP-1 Pump Mfg: Taco Model: #006 w/ 00 Timer/Aquastat | D120: 1 | E120: 0 | F120: =CEILING(SUM(D120:D120)*(1+E120),1) -> 1 | G120: EA | H120: 3.65 | I120: =H120*F120 -> 3.65 | J120: 48 | K120: =J120*I120 -> 175.2 | L120: 212.76 | M120: =L120*F120 -> 212.76 | N120: =M120+K120 -> 387.96
A121: =IF(G121<>"",1+MAX($A$8:A120),"")
A122: =IF(G122<>"",1+MAX($A$8:A121),"") | C122: Water Heater
A123: =IF(G123<>"",1+MAX($A$8:A122),"") -> 99 | C123: GWH-1 Electric Water Heater Mfg: A.O Smith BTH-400(A) Capacity: 119 Gal. | D123: 1 | E123: 0 | F123: =CEILING(SUM(D123:D123)*(1+E123),1) -> 1 | G123: EA | H123: 12 | I123: =H123*F123 -> 12 | J123: 48 | K123: =J123*I123 -> 576 | L123: 15554 | M123: =L123*F123 -> 15554 | N123: =M123+K123 -> 16130
A124: =IF(G124<>"",1+MAX($A$8:A123),"")
A125: =IF(G125<>"",1+MAX($A$8:A124),"") | C125: Meter
A126: =IF(G126<>"",1+MAX($A$8:A125),"") -> 100 | C126: Natural Gas Utility Meter | D126: 1 | E126: 0 | F126: =CEILING(SUM(D126:D126)*(1+E126),1) -> 1 | G126: EA | H126: 4.2 | I126: =H126*F126 -> 4.2 | J126: 48 | K126: =J126*I126 -> 201.6 | L126: 1205 | M126: =L126*F126 -> 1205 | N126: =M126+K126 -> 1406.6
A127: =IF(G127<>"",1+MAX($A$8:A126),"")
A128: =IF(G128<>"",1+MAX($A$8:A127),"") | C128: Accessories
A129: =IF(G129<>"",1+MAX($A$8:A128),"") -> 101 | C129: Gas Cock | D129: 1 | E129: 0 | F129: =CEILING(SUM(D129:D129)*(1+E129),1) -> 1 | G129: EA | H129: 0.5 | I129: =H129*F129 -> 0.5 | J129: 48 | K129: =J129*I129 -> 24 | L129: 32 | M129: =L129*F129 -> 32 | N129: =M129+K129 -> 56
A130: =IF(G130<>"",1+MAX($A$8:A129),"") -> 102 | C130: Gas Utility Regulator | D130: 1 | E130: 0 | F130: =CEILING(SUM(D130:D130)*(1+E130),1) -> 1 | G130: EA | H130: 0.65 | I130: =H130*F130 -> 0.65 | J130: 48 | K130: =J130*I130 -> 31.2 | L130: 65 | M130: =L130*F130 -> 65 | N130: =M130+K130 -> 96.2
A131: =IF(G131<>"",1+MAX($A$8:A130),"")
A132: =IF(G132<>"",1+MAX($A$8:A131),"") | C132: Grease Trap
A133: =IF(G133<>"",1+MAX($A$8:A132),"") -> 103 | C133: Grease Trap | D133: 1 | E133: 0 | F133: =CEILING(SUM(D133:D133)*(1+E133),1) -> 1 | G133: EA | H133: 12 | I133: =H133*F133 -> 12 | J133: 48 | K133: =J133*I133 -> 576 | L133: 8650 | M133: =L133*F133 -> 8650 | N133: =M133+K133 -> 9226
A134: =IF(G134<>"",1+MAX($A$8:A133),"")
A135: SUB TOTAL | I135: =SUM(I8:I134) -> 1015.329 | K135: =SUM(K8:K134) -> 63735.792 | M135: =SUM(M8:M134) -> 110451.78 | N135: =SUM(N8:N134) -> 174187.58 | O135: =SUM(O8:O134) -> 174187.58
C139: GENERAL REQUIREMENTS | D139: 01 00
C140: SITE CONDITIONS | D140: 02 00
C141: CONCRETE | D141: 03 00
C142: MASONRY | D142: 04 00
C143: METAL | D143: 05 00
C144: WOOD, PLASTICS & COMPOSITES | D144: 06 00
C145: WATERPROOFING | D145: 07 00
C146: OPENNINGS | D146: 08 00
C147: FINISHES | D147: 09 00
C148: SPECIALITES | D148: 10 00
C149: EQUIPMENT | D149: 11 00
C150: FURNISHINGS | D150: 12 00
... C162: UTILITIES | D162: 33 00
