Workbook

Sheet Planting
A2: Project: | B2: SR 510 Yelm Loop
A4: Address: | B4: SR 510 Yelm Loop New Alignment Phase 2
A6: Scope: | B6: SELF-PERFORM LANDSCAPE – Gold Standard (Raw)
A8: Date: | B8: 46193
A9: SR# | B9: REF | C9: DESCRIPTION | D9: QTY | E9: UNIT | F9: WASTAGE | G9: QTY W/ WASTAGE | H9: MATERIAL RATE | I9: LABOR RATE | J9: EQUIP RATE | K9: MATERIAL COSTS | L9: LABOR COSTS | M9: EQUIP COSTS | N9: SUB COST
A10: DIV 01 – MOBILIZATION / GENERAL REQUIREMENTS (LIMITED SCOPE)
A11: 1 | C11: Mobilization / Demobilization – Planting Crew | D11: 1 | E11: LS | F11: 0 | G11: =D11*(1+F11) -> 1 | H11: 0 | I11: 3000 | J11: 800 | K11: =G11*H11 -> 0 | L11: =G11*I11 -> 3000 | M11: =G11*J11 -> 800 | N11: =K11+L11+M11 -> 3800
A12: 2 | C12: Project Foreman – PLA/Prevailing Wage (4 weeks) | D12: 160 | E12: HR | F12: 0 | G12: =D12*(1+F12) -> 160 | H12: 0 | I12: 75 | J12: 0 | K12: =G12*H12 -> 0 | L12: =G12*I12 -> 12000 | M12: =G12*J12 -> 0 | N12: =K12+L12+M12 -> 12000
A13: 3 | C13: Safety Orientation / WSDOT Site Training | D13: 1 | E13: EA | F13: 0 | G13: =D13*(1+F13) -> 1 | H13: 300 | I13: 2000 | J13: 0 | K13: =G13*H13 -> 300 | L13: =G13*I13 -> 2000 | M13: =G13*J13 -> 0 | N13: =K13+L13+M13 -> 2300
A14: 4 | C14: Submittal Preparation – Plant List & Soil Amendments | D14: 1 | E14: LS | F14: 0 | G14: =D14*(1+F14) -> 1 | H14: 0 | I14: 2500 | J14: 0 | K14: =G14*H14 -> 0 | L14: =G14*I14 -> 2500 | M14: =G14*J14 -> 0 | N14: =K14+L14+M14 -> 2500
A15: 5 | C15: Site Cleanup & Final Demobilization | D15: 1 | E15: LS | F15: 0 | G15: =D15*(1+F15) -> 1 | H15: 200 | I15: 1500 | J15: 400 | K15: =G15*H15 -> 200 | L15: =G15*I15 -> 1500 | M15: =G15*J15 -> 400 | N15: =K15+L15+M15 -> 2100
A16: SUBTOTAL – GEN REQ | N16: =SUM(N11:N15) -> 22700
A18: DIV 32 – UPLAND PLANT MIX (UP) – Container Stock
A19: 1 | B19: 32000 | C19: Western Serviceberry (Amelanchier alnifolia) – #2 Cont. | D19: 32 | E19: EA | F19: 0 | G19: =D19*(1+F19) -> 32 | H19: 18 | I19: 9 | J19: 0 | K19: =G19*H19 -> 576 | L19: =G19*I19 -> 288 | M19: =G19*J19 -> 0 | N19: =K19+L19+M19 -> 864
A20: 2 | B20: 32000 | C20: Cascara (Frangula purshiana) – #2 Cont. | D20: 32 | E20: EA | F20: 0 | G20: =D20*(1+F20) -> 32 | H20: 18 | I20: 9 | J20: 0 | K20: =G20*H20 -> 576 | L20: =G20*I20 -> 288 | M20: =G20*J20 -> 0 | N20: =K20+L20+M20 -> 864
A21: 3 | B21: 32000 | C21: Red Oak (Quercus rubra) – #2 Cont. (12-24" HT) | D21: 35 | E21: EA | F21: 0 | G21: =D21*(1+F21) -> 35 | H21: 65 | I21: 18 | J21: 0 | K21: =G21*H21 -> 2275 | L21: =G21*I21 -> 630 | M21: =G21*J21 -> 0 | N21: =K21+L21+M21 -> 2905
A22: 4 | B22: 32000 | C22: Oceanspray (Holodiscus discolor) – #1 Cont. | D22: 822 | E22: EA | F22: 0 | G22: =D22*(1+F22) -> 822 | H22: 14 | I22: 7 | J22: 0 | K22: =G22*H22 -> 11508 | L22: =G22*I22 -> 5754 | M22: =G22*J22 -> 0 | N22: =K22+L22+M22 -> 17262
A23: 5 | B23: 32000 | C23: Red-Flowering Currant (Ribes sanguineum) – #1 Cont. | D23: 1096 | E23: EA | F23: 0 | G23: =D23*(1+F23) -> 1096 | H23: 14 | I23: 7 | J23: 0 | K23: =G23*H23 -> 15344 | L23: =G23*I23 -> 7672 | M23: =G23*J23 -> 0 | N23: =K23+L23+M23 -> 23016
A24: 6 | B24: 32000 | C24: Nootka Rose (Rosa nutkana) – #1 Cont. | D24: 822 | E24: EA | F24: 0 | G24: =D24*(1+F24) -> 822 | H24: 12 | I24: 7 | J24: 0 | K24: =G24*H24 -> 9864 | L24: =G24*I24 -> 5754 | M24: =G24*J24 -> 0 | N24: =K24+L24+M24 -> 15618
A25: SUBTOTAL – UPLAND PLANT MIX | N25: =SUM(N19:N24) -> 60529
A27: DIV 32 – RIPARIAN PLANT MIX (RP) – Container Stock
A28: 1 | B28: 32000 | C28: Oceanspray (Holodiscus discolor) – #1 Cont. | D28: 252 | E28: EA | F28: 0 | G28: =D28*(1+F28) -> 252 | H28: 14 | I28: 7 | J28: 0 | K28: =G28*H28 -> 3528 | L28: =G28*I28 -> 1764 | M28: =G28*J28 -> 0 | N28: =K28+L28+M28 -> 5292
A29: 2 | B29: 32000 | C29: Red-Flowering Currant (Ribes sanguineum) – #1 Cont. | D29: 252 | E29: EA | F29: 0 | G29: =D29*(1+F29) -> 252 | H29: 14 | I29: 7 | J29: 0 | K29: =G29*H29 -> 3528 | L29: =G29*I29 -> 1764 | M29: =G29*J29 -> 0 | N29: =K29+L29+M29 -> 5292
A30: 3 | B30: 32000 | C30: Nootka Rose (Rosa nutkana) – #1 Cont. | D30: 252 | E30: EA | F30: 0 | G30: =D30*(1+F30) -> 252 | H30: 12 | I30: 7 | J30: 0 | K30: =G30*H30 -> 3024 | L30: =G30*I30 -> 1764 | M30: =G30*J30 -> 0 | N30: =K30+L30+M30 -> 4788
A31: 4 | B31: 32000 | C31: Salmonberry (Rubus spectabilis) – #1 Cont. | D31: 252 | E31: EA | F31: 0 | G31: =D31*(1+F31) -> 252 | H31: 14 | I31: 7 | J31: 0 | K31: =G31*H31 -> 3528 | L31: =G31*I31 -> 1764 | M31: =G31*J31 -> 0 | N31: =K31+L31+M31 -> 5292
A32: 5 | B32: 32000 | C32: Red Elderberry (Sambucus racemosa) – #1 Cont. | D32: 252 | E32: EA | F32: 0 | G32: =D32*(1+F32) -> 252 | H32: 14 | I32: 7 | J32: 0 | K32: =G32*H32 -> 3528 | L32: =G32*I32 -> 1764 | M32: =G32*J32 -> 0 | N32: =K32+L32+M32 -> 5292
A33: SUBTOTAL – RIPARIAN PLANT MIX | N33: =SUM(N28:N32) -> 25956
A35: DIV 32 – LIVE STAKES (LS) – Willow & Dogwood
A36: 1 | B36: 32000 | C36: Red-Osier Dogwood (Cornus sericea) – 24-48" LIVE STAKE @ 3' o.c. | D36: 82 | E36: EA | F36: 0 | G36: =D36*(1+F36) -> 82 | H36: 5.5 | I36: 4.5 | J36: 0 | K36: =G36*H36 -> 451 | L36: =G36*I36 -> 369 | M36: =G36*J36 -> 0 | N36: =K36+L36+M36 -> 820
A37: 2 | B37: 32000 | C37: Hooker's Willow (Salix hookeriana) – 24-48" LIVE STAKE @ 3' o.c. | D37: 163 | E37: EA | F37: 0 | G37: =D37*(1+F37) -> 163 | H37: 5.5 | I37: 4.5 | J37: 0 | K37: =G37*H37 -> 896.5 | L37: =G37*I37 -> 733.5 | M37: =G37*J37 -> 0 | N37: =K37+L37+M37 -> 1630
A38: 3 | B38: 32000 | C38: Sitka Willow (Salix sitchensis) – 24-48" LIVE STAKE @ 3' o.c. | D38: 163 | E38: EA | F38: 0 | G38: =D38*(1+F38) -> 163 | H38: 5.5 | I38: 4.5 | J38: 0 | K38: =G38*H38 -> 896.5 | L38: =G38*I38 -> 733.5 | M38: =G38*J38 -> 0 | N38: =K38+L38+M38 -> 1630
A39: SUBTOTAL – LIVE STAKES | N39: =SUM(N36:N38) -> 4080
A41: DIV 32 – PLANT LAYOUT / LOCALIZED SOIL AMENDMENT / MULCH RINGS
A42: 1 | B42: 32000 | C42: Plant Layout & Staking (field locate per plan) | D42: 1 | E42: LS | F42: 0 | G42: =D42*(1+F42) -> 1 | H42: 0 | I42: 4800 | J42: 0 | K42: =G42*H42 -> 0 | L42: =G42*I42 -> 4800 | M42: =G42*J42 -> 0 | N42: =K42+L42+M42 -> 4800
A43: 2 | B43: 32000 | C43: Localized Planting Soil / Amendment (per plant pit – avg 2 CF/plant) | D43: 4099 | E43: CF | F43: 0 | G43: =D43*(1+F43) -> 4099 | H43: 0.45 | I43: 0.2 | J43: 0 | K43: =G43*H43 -> 1844.55 | L43: =G43*I43 -> 819.8 | M43: =G43*J43 -> 0 | N43: =K43+L43+M43 -> 2664.35
A44: 3 | B44: 32000 | C44: Mulch Rings / Plant Saucers (3" depth, 24" dia, per plant) | D44: 4099 | E44: EA | F44: 0 | G44: =D44*(1+F44) -> 4099 | H44: 0.18 | I44: 0.12 | J44: 0 | K44: =G44*H44 -> 737.82 | L44: =G44*I44 -> 491.88 | M44: =G44*J44 -> 0 | N44: =K44+L44+M44 -> 1229.7
A45: 4 | B45: 32000 | C45: Landscape Punch-List / Deficiency Walk & Correction | D45: 1 | E45: LS | F45: 0 | G45: =D45*(1+F45) -> 1 | H45: 0 | I45: 2800 | J45: 0 | K45: =G45*H45 -> 0 | L45: =G45*I45 -> 2800 | M45: =G45*J45 -> 0 | N45: =K45+L45+M45 -> 2800
A46: SUBTOTAL – LAYOUT / SOIL / MULCH RINGS | N46: =SUM(N42:N45) -> 11494.05
A48: PLANTING TAB – TOTAL RAW COST (Base Bid) | N48: =N16+N25+N33+N39+N46 -> 124759.05
A50: ⛔ EXCLUDED FROM THIS SHEET (per Rev-04 scope): Hydroseeding, full-site seeding, full-site bark mulch, fine grading, topsoil stripping, CAVFS, MVFS, CABS, bioretention, underdrain, check dams, irrigation, temp watering, traffic control, TESC beyond GS work area, civil earthwork.

Sheet Commercial
A2: Project: | B2: SR 510 Yelm Loop
A4: Address: | B4: SR 510 Yelm Loop New Alignment Phase 2
A6: Scope: | B6: SELF-PERFORM LANDSCAPE – Gold Standard (Raw)
A8: Date: | B8: 46193
A9: SR# | B9: REF | C9: DESCRIPTION | D9: BASIS | E9: RATE | F9: UNIT | G9: QTY | H9: UNIT COST | I9: SUB COST
A10: DIV 01 – COMMERCIAL CARRY / GENERAL REQUIREMENTS (LIMITED SCOPE ONLY)
A11: 1 | C11: General Liability Insurance | D11: % of contract value (1.5%) | E11: =0.015 -> 0.015 | F11: LS | G11: 1 | H11: 4500 | I11: 4500
A12: 2 | C12: Performance & Payment Bond | D12: % of contract value (1.5%) | E12: =0.015 -> 0.015 | F12: LS | G12: 1 | H12: 5000 | I12: 5000
A13: 3 | C13: Mobilization / Demob (Landscape Crew Only) | D13: Lump Sum | F13: LS | G13: 1 | H13: 3800 | I13: 3800
A14: 4 | C14: Project Foreman – Site Supervision (4 Weeks PLA) | D14: 4 wks × $4,800/wk | E14: 4800 | F14: WK | G14: 4 | H14: 4800 | I14: 19200
A15: 5 | C15: Certified Payroll Administration (WSDOT/PLA) | D15: 20 hrs @ $150/hr | E15: 150 | F15: HR | G15: 20 | H15: 150 | I15: 3000
A16: 6 | C16: WSDOT Compliance / Submittal Administration | D16: Lump Sum | F16: LS | G16: 1 | H16: 3500 | I16: 3500
A17: 7 | C17: Submittals / RFI Administration | D17: Lump Sum | F17: LS | G17: 1 | H17: 2500 | I17: 2500
A18: 8 | C18: Closeout Documentation / As-Builts | D18: Lump Sum | F18: LS | G18: 1 | H18: 1800 | I18: 1800
A19: 9 | C19: Landscape Punch-List Administration | D19: Lump Sum | F19: LS | G19: 1 | H19: 1200 | I19: 1200
A20: 10 | C20: Small Tools & Consumables Allowance | D20: Allowance | F20: LS | G20: 1 | H20: 1500 | I20: 1500
A21: COMMERCIAL CARRY – SUBTOTAL | I21: =SUM(I11:I20) -> 46000
A23: ⚠ NOTE: Rev-04 commercial carry is scaled to a limited planting-only scope (~$300K–$500K). Full-scope commercial carry from Rev-03 ($260K) is NOT applicable here. Insurance and bond carried as flat amounts scaled to this package.

Sheet Establishment
A2: Project: | B2: SR 510 Yelm Loop
A4: Address: | B4: SR 510 Yelm Loop New Alignment Phase 2
A6: Scope: | B6: SELF-PERFORM LANDSCAPE – Gold Standard (Raw)
A8: Date: | B8: 46193
A9: SR# | B9: REF | C9: DESCRIPTION | D9: DURATION | E9: QTY | F9: UNIT | G9: WASTAGE | H9: QTY W/ WASTAGE | I9: MAT RATE | J9: LAB RATE | K9: EQ RATE | L9: MAT COST | M9: LAB COST | N9: EQ COST | O9: SUB COST
A10: DIV 01 – CLOSEOUT / DOCUMENTATION
A11: 1 | C11: Closeout Documentation / As-Builts (carried once in Commercial tab – not duplicated here) | D11: End of project | E11: 1 | F11: LS | G11: 0 | H11: =E11*(1+G11) -> 1 | I11: 0 | J11: 1800 | K11: 0 | L11: =H11*I11 -> 0 | M11: =H11*J11 -> 1800 | N11: =H11*K11 -> 0 | O11: =L11+M11+N11 -> 1800
A12: SUBTOTAL – CLOSEOUT | O12: =SUM(O11:O11) -> 1800
A14: DIV 32 – PLANT ESTABLISHMENT & MAINTENANCE (BASE BID – YEAR 1 + YEAR 2)
A15: 1 | B15: 32000 | C15: Plant Establishment Period – Year 1 (labor, materials, watering) | D15: 12 months | E15: 1 | F15: LS | G15: 0 | H15: =E15*(1+G15) -> 1 | I15: 3000 | J15: 10000 | K15: 1000 | L15: =H15*I15 -> 3000 | M15: =H15*J15 -> 10000 | N15: =H15*K15 -> 1000 | O15: =L15+M15+N15 -> 14000
A16: 2 | B16: 32000 | C16: Plant Establishment Period – Year 2 (if required per spec) | D16: 12 months | E16: 1 | F16: LS | G16: 0 | H16: =E16*(1+G16) -> 1 | I16: 1500 | J16: 6000 | K16: 800 | L16: =H16*I16 -> 1500 | M16: =H16*J16 -> 6000 | N16: =H16*K16 -> 800 | O16: =L16+M16+N16 -> 8300
A17: 3 | B17: 32000 | C17: Weed Control / Maintenance Visits (18 visits × 4 hrs) | D17: Per visit | E17: 18 | F17: Visit | G17: 0 | H17: =E17*(1+G17) -> 18 | I17: 0 | J17: 280 | K17: 0 | L17: =H17*I17 -> 0 | M17: =H17*J17 -> 5040 | N17: =H17*K17 -> 0 | O17: =L17+M17+N17 -> 5040
A18: 4 | B18: 32000 | C18: Fertilization Applications – Establishment Period (4 applications) | D18: Per app | E18: 4 | F18: APP | G18: 0 | H18: =E18*(1+G18) -> 4 | I18: 350 | J18: 250 | K18: 0 | L18: =H18*I18 -> 1400 | M18: =H18*J18 -> 1000 | N18: =H18*K18 -> 0 | O18: =L18+M18+N18 -> 2400
A19: 5 | B19: 32000 | C19: Plant Replacement Allowance (warranty – 10% of plants) | D19: Warranty | E19: 1 | F19: LS | G19: 0 | H19: =E19*(1+G19) -> 1 | I19: 3500 | J19: 1500 | K19: 0 | L19: =H19*I19 -> 3500 | M19: =H19*J19 -> 1500 | N19: =H19*K19 -> 0 | O19: =L19+M19+N19 -> 5000
A20: 6 | B20: 32000 | C20: Re-seeding Failed Areas – Localized Only (warranty allowance) | D20: Warranty | E20: 1 | F20: LS | G20: 0 | H20: =E20*(1+G20) -> 1 | I20: 800 | J20: 600 | K20: 0 | L20: =H20*I20 -> 800 | M20: =H20*J20 -> 600 | N20: =H20*K20 -> 0 | O20: =L20+M20+N20 -> 1400
A21: 7 | B21: 32000 | C21: Final Inspection & WSDOT Acceptance Walk | D21: End of warranty | E21: 1 | F21: LS | G21: 0 | H21: =E21*(1+G21) -> 1 | I21: 0 | J21: 1800 | K21: 0 | L21: =H21*I21 -> 0 | M21: =H21*J21 -> 1800 | N21: =H21*K21 -> 0 | O21: =L21+M21+N21 -> 1800
A22: SUBTOTAL – ESTABLISHMENT (BASE BID – YR 1 & YR 2) | O22: =SUM(O15:O21) -> 37940
A24: ★ ADD-ALTERNATE AA-03 – YEAR 3 PLANT ESTABLISHMENT (NOT IN BASE BID)
A25: 2A | B25: 32000 | C25: Plant Establishment Period – Year 3 (ADD-ALTERNATE AA-03 – if required by spec) | D25: 12 months | E25: 1 | F25: LS | G25: 0 | H25: =E25*(1+G25) -> 1 | I25: 1200 | J25: 4500 | K25: 300 | L25: =H25*I25 -> 1200 | M25: =H25*J25 -> 4500 | N25: =H25*K25 -> 300 | O25: =L25+M25+N25 -> 6000
A26: ADD-ALTERNATE AA-03 TOTAL (Year 3 Establishment – NOT in base bid) | O26: =O25 -> 6000
A28: ESTABLISHMENT TAB – TOTAL RAW COST (BASE BID, Yr1+Yr2 only) | O28: =O12+O22 -> 39740

Sheet Add-Alternates
A2: Project: | B2: SR 510 Yelm Loop
A4: Address: | B4: SR 510 Yelm Loop New Alignment Phase 2
A6: Scope: | B6: SELF-PERFORM LANDSCAPE – Gold Standard (Raw)
A8: Date: | B8: 46193
A9: SR# | B9: REF | C9: DESCRIPTION | D9: QTY | E9: UNIT | F9: WASTAGE | G9: QTY W/ WASTAGE | H9: MAT RATE | I9: LAB RATE | J9: EQ RATE | K9: MAT COST | L9: LAB COST | M9: EQ COST | N9: SUB COST
A10: ★ ADD-ALTERNATE AA-01 – CAVFS ONLY (Compost Amended Vegetated Filter Strip, 2.66 AC)
A11: 1 | B11: 32000 | C11: CAVFS – Compost Amended Vegetated Filter Strip prep & install (2.66 AC = 115,870 SF) | D11: 115870 | E11: SF | F11: 0 | G11: =D11*(1+F11) -> 115870 | H11: 0.85 | I11: 0.22 | J11: 0 | K11: =G11*H11 -> 98489.5 | L11: =G11*I11 -> 25491.4 | M11: =G11*J11 -> 0 | N11: =K11+L11+M11 -> 123980.9
A12: 2 | B12: 32000 | C12: CAVFS – Fine Grading / Surface Prep (included in CAVFS unit rate) | D12: 115870 | E12: SF | F12: 0 | G12: =D12*(1+F12) -> 115870 | H12: 0 | I12: 0.05 | J12: 0.04 | K12: =G12*H12 -> 0 | L12: =G12*I12 -> 5793.5 | M12: =G12*J12 -> 4634.8 | N12: =K12+L12+M12 -> 10428.3
A13: AA-01 SUBTOTAL – CAVFS RAW COST | N13: =SUM(N11:N12) -> 134409.2
A15: ★ ADD-ALTERNATE AA-02 – CABS / BIORETENTION LIMITED INTERFACE (0.10 AC + 0.83 AC)
A16: 1 | B16: 32000 | C16: CABS – Compost Amended Biofiltration Swale install (0.10 AC = 4,356 SF) | D16: 4356 | E16: SF | F16: 0 | G16: =D16*(1+F16) -> 4356 | H16: 5.28 | I16: 3 | J16: 0 | K16: =G16*H16 -> 22999.68 | L16: =G16*I16 -> 13068 | M16: =G16*J16 -> 0 | N16: =K16+L16+M16 -> 36067.68
A17: 2 | B17: 32000 | C17: Biofiltration Area Prep & Grading (0.83 AC = 36,155 SF) | D17: 36155 | E17: SF | F17: 0 | G17: =D17*(1+F17) -> 36155 | H17: 0 | I17: 0.25 | J17: 0 | K17: =G17*H17 -> 0 | L17: =G17*I17 -> 9038.75 | M17: =G17*J17 -> 0 | N17: =K17+L17+M17 -> 9038.75
A18: 3 | B18: 32000 | C18: Check Dam / Flow Spreader Installation (150 EA, per bioretention detail) | D18: 150 | E18: EA | F18: 0 | G18: =D18*(1+F18) -> 150 | H18: 180 | I18: 40 | J18: 0 | K18: =G18*H18 -> 27000 | L18: =G18*I18 -> 6000 | M18: =G18*J18 -> 0 | N18: =K18+L18+M18 -> 33000
A19: 4 | B19: 32000 | C19: Underdrain Piping – Landscape Bioretention Interface (assumed 359 LF, confirm civil) | D19: 359 | E19: LF | F19: 0 | G19: =D19*(1+F19) -> 359 | H19: 180 | I19: 38 | J19: 0 | K19: =G19*H19 -> 64620 | L19: =G19*I19 -> 13642 | M19: =G19*J19 -> 0 | N19: =K19+L19+M19 -> 78262
A20: AA-02 SUBTOTAL – CABS/BIORETENTION RAW COST | N20: =SUM(N16:N19) -> 156368.43
A22: ★ ADD-ALTERNATE AA-03 – YEAR 3 PLANT ESTABLISHMENT (if required by spec)
A23: 1 | B23: 32000 | C23: Plant Establishment Period – Year 3 (12 months, reduced frequency) | D23: 1 | E23: LS | F23: 0 | G23: =D23*(1+F23) -> 1 | H23: 1200 | I23: 4500 | J23: 300 | K23: =G23*H23 -> 1200 | L23: =G23*I23 -> 4500 | M23: =G23*J23 -> 300 | N23: =K23+L23+M23 -> 6000
A24: AA-03 SUBTOTAL – YEAR 3 ESTABLISHMENT RAW COST | N24: =SUM(N23:N23) -> 6000
A26: ★ ADD-ALTERNATE AA-04 – TEMPORARY WATERING (only if Atkinson formally requests in writing)
A27: 1 | B27: 32000 | C27: Temporary Water Supply / Connection to Source (allowance) | D27: 1 | E27: LS | F27: 0 | G27: =D27*(1+F27) -> 1 | H27: 2500 | I27: 1500 | J27: 0 | K27: =G27*H27 -> 2500 | L27: =G27*I27 -> 1500 | M27: =G27*J27 -> 0 | N27: =K27+L27+M27 -> 4000
A28: 2 | B28: 32000 | C28: Temporary Drip / Soaker System Install & Removal (planting areas only) | D28: 4099 | E28: EA | F28: 0 | G28: =D28*(1+F28) -> 4099 | H28: 1.8 | I28: 1.2 | J28: 0 | K28: =G28*H28 -> 7378.2 | L28: =G28*I28 -> 4918.8 | M28: =G28*J28 -> 0 | N28: =K28+L28+M28 -> 12297
A29: 3 | B29: 32000 | C29: Water Truck / Hauled Water (allowance – 8 visits) | D29: 8 | E29: Visit | F29: 0 | G29: =D29*(1+F29) -> 8 | H29: 350 | I29: 280 | J29: 120 | K29: =G29*H29 -> 2800 | L29: =G29*I29 -> 2240 | M29: =G29*J29 -> 960 | N29: =K29+L29+M29 -> 6000
A30: 4 | B30: 32000 | C30: Temporary Watering Labor & Monitoring (Year 1) | D30: 1 | E30: LS | F30: 0 | G30: =D30*(1+F30) -> 1 | H30: 0 | I30: 4200 | J30: 0 | K30: =G30*H30 -> 0 | L30: =G30*I30 -> 4200 | M30: =G30*J30 -> 0 | N30: =K30+L30+M30 -> 4200
A31: AA-04 SUBTOTAL – TEMPORARY WATERING RAW COST | N31: =SUM(N27:N30) -> 26497
A33: ADD-ALTERNATE SUMMARY (Raw Costs Before Markup) | N33: RAW COST
A34: AA-01 – CAVFS Only | N34: =N13 -> 134409.2
A35: AA-02 – CABS / Bioretention Interface | N35: =N20 -> 156368.43
A36: AA-03 – Year 3 Plant Establishment | N36: =N24 -> 6000
A37: AA-04 – Temporary Watering | N37: =N31 -> 26497
A38: TOTAL ALL ADD-ALTERNATES (if all accepted) | N38: =N34+N35+N36+N37 -> 323274.63

Sheet Crew Schedule
A2: Project: | B2: SR 510 Yelm Loop
A4: Address: | B4: SR 510 Yelm Loop New Alignment Phase 2
A6: Scope: | B6: SELF-PERFORM LANDSCAPE – Gold Standard (Raw)
A8: Date: | B8: 46193
A9: SCOPE CATEGORY | B9: DIVISION | C9: CREW COMPOSITION | D9: CREW SIZE | E9: LABOR CLASS | F9: TOTAL LABOR HRS | G9: EQUIP HRS | H9: PRODUCTION BASIS | I9: DURATION (WEEKS) | J9: PERFORM BY | K9: STATUS / NOTE | L9: REF
A10: DIVISION 01 – GENERAL REQUIREMENTS (LIMITED SCOPE)
A11: Mobilization & Demobilization | B11: Div 01 | C11: Foreman + 1 Laborer | D11: 2 | E11: Foreman / Laborer | F11: 16 | G11: – | H11: 1 mob + 1 demob | I11: 0.5 | J11: Self-Perform | K11: Limited scope mob – planting crew only | L11: 01000
A12: Project Foreman – Site Supervision (PLA) | B12: Div 01 | C12: Foreman only | D12: 1 | E12: Landscape Foreman (PLA) | F12: 160 | G12: – | H12: 4 wks × 40 hrs/wk | I12: 4 | J12: Self-Perform | K12: Certified payroll; union rate applied | L12: 01000
A13: Safety Orientation / WSDOT Site Training | B13: Div 01 | C13: All crew | D13: 4 | E13: Mixed | F13: 8 | G13: – | H13: 1-day orientation | I13: 0.2 | J13: Self-Perform | K13: One-time; all trades | L13: 01000
A14: Submittals (plant list, soil amendments) | B14: Div 01 | C14: PM / Admin | D14: 1 | E14: Project Manager | F14: 20 | G14: – | H14: Lump Sum | I14: 0.5 | J14: Self-Perform | K14: Plant list + soil spec only (no hydro/seed mixes) | L14: 01000
A15: Closeout / As-Builts | B15: Div 01 | C15: PM / Admin | D15: 1 | E15: Project Manager | F15: 16 | G15: – | H15: Lump Sum | I15: 0.5 | J15: Self-Perform | K15: Limited scope closeout documentation | L15: 01000
A16: DIVISION 32 – PLANTING (BASE SCOPE)
A17: Plant Layout & Staking (per plan) | B17: Div 32 | C17: Foreman + 1 Laborer | D17: 2 | E17: Laborer / Foreman | F17: 40 | G17: – | H17: ~60 plants/hr/crew located & flagged | I17: 1 | J17: Self-Perform | K17: All plants located before digging | L17: 32000
A18: Upland Plant Mix – Container Stock (2,839 plants) | B18: Div 32 | C18: Foreman + 3 Laborers | D18: 4 | E18: Laborer / Foreman | F18: 189.3 | G18: – | H18: 15 plants/hr/crew (container stock) | I18: 4.3 | J18: Self-Perform | K18: Upland shrubs: 6 species × 2,839 total | L18: 32000
A19: Riparian Plant Mix – Container Stock (1,260 plants) | B19: Div 32 | C19: Foreman + 3 Laborers | D19: 4 | E19: Laborer / Foreman | F19: 84 | G19: – | H19: 15 plants/hr/crew (container stock) | I19: 2 | J19: Self-Perform | K19: Riparian shrubs: 5 species × 1,260 total | L19: 32000
A20: Live Stakes – Willow & Dogwood (408 EA) | B20: Div 32 | C20: 2 Laborers | D20: 2 | E20: Laborer | F20: 41 | G20: – | H20: 10 stakes/hr/person | I20: 1 | J20: Self-Perform | K20: 3 species, hand-driven | L20: 32000
A21: Localized Soil Amendment / Plant Pits (4,099 plants) | B21: Div 32 | C21: Foreman + 2 Laborers | D21: 3 | E21: Laborer / Foreman | F21: 60 | G21: 8 | H21: Manual & mini-excavator spot work | I21: 1.5 | J21: Self-Perform | K21: Per-plant pit soil amendment only (not full-site) | L21: 32000
A22: Mulch Rings / Plant Saucers (4,099 EA) | B22: Div 32 | C22: 2 Laborers | D22: 2 | E22: Laborer | F22: 50 | G22: – | H22: ~50 rings/hr (hand apply) | I22: 1 | J22: Self-Perform | K22: 24" dia × 3" depth per plant only | L22: 32000
A23: Punch-List / Landscape Deficiency Walk | B23: Div 32 | C23: Foreman | D23: 1 | E23: Landscape Foreman | F23: 16 | G23: – | H23: End of planting | I23: 0.5 | J23: Self-Perform | K23: Final walk, tag, and replacement | L23: 32000
A24: PLANT ESTABLISHMENT (BASE – YR 1 + YR 2)
A25: Year 1 Establishment (12 months) | B25: Div 32 | C25: Foreman + 2 Laborers | D25: 3 | E25: Laborer / Foreman | F25: 280 | G25: – | H25: Monthly visits × 12 months | I25: Ongoing | J25: Self-Perform | K25: Watering, weeding, inspection, correction | L25: 32000
A26: Year 2 Establishment (if required) | B26: Div 32 | C26: Foreman + 1 Laborer | D26: 2 | E26: Laborer / Foreman | F26: 180 | G26: – | H26: Bi-monthly visits × 12 months | I26: Ongoing | J26: Self-Perform | K26: Reduced frequency – Year 2 | L26: 32000
A27: Weed Control (18 visits) | B27: Div 32 | C27: 2-man crew | D27: 2 | E27: Laborer | F27: 144 | G27: – | H27: 8 hrs/visit | I27: Ongoing | J27: Self-Perform | L27: 32000
A28: Fertilization (4 applications) | B28: Div 32 | C28: 2-man crew | D28: 2 | E28: Laborer | F28: 32 | G28: – | H28: 8 hrs/app | I28: Ongoing | J28: Self-Perform | L28: 32000
A29: Plant Replacement (10% allowance) | B29: Div 32 | C29: Foreman + 2 Laborers | D29: 3 | E29: Laborer / Foreman | F29: 60 | G29: – | H29: Allowance | I29: Warranty | J29: Self-Perform | K29: Warranty obligation | L29: 32000
A30: Final Inspection / WSDOT Acceptance Walk | B30: Div 32 | C30: PM + Foreman | D30: 2 | E30: PM / Foreman | F30: 8 | G30: – | H30: 1-day walk | I30: End | J30: Self-Perform | L30: 32000
A31: ⛔ EXCLUDED FROM REV-04 BASE BID (available as Add-Alternates AA-01 to AA-04)
A32: ⛔ Hydroseeding / Full-Site Seeding (all mix types)
A33: ⛔ Full-Site 3" Bark Mulch (1,257,578 SF)
A34: ⛔ Fine Grading – Landscape Areas
A35: ⛔ Topsoil Stripping & Stockpiling
A36: ⛔ CAVFS / MVFS (AA-01 if requested)
A37: ⛔ CABS / Bioretention Interface (AA-02 if requested)
A38: ⛔ Underdrain Piping / Check Dams / Flow Spreaders (AA-02)
A39: ⛔ Irrigation (permanent or temporary) – AA-04 if formally directed
A40: ⛔ Traffic Control / TESC beyond GS work area
A41: ⛔ Civil Earthwork / Year 3 Establishment (AA-03)
A43: TOTAL SELF-PERFORM LABOR HRS (LIMITED SCOPE ESTIMATE) | F43: ~1,404 hrs | G43: ESTIMATED FIELD DURATION: ~6–8 weeks (planting) + 24 months establishment

Sheet SUMMARY
A2: Project: | B2: SR 510 Yelm Loop
A4: Address: | B4: SR 510 Yelm Loop New Alignment Phase 2
A6: Date: | B6: 46193
A7: DIV. NO. | B7: DESCRIPTION | C7: TOTAL DIV. COST | D7: NOTES
A8: BASE BID – LIMITED GOLD STANDARD LANDSCAPE PACKAGE
A9: 1 | B9: Planting – Upland Mix, Riparian Mix, Live Stakes, Layout, Soil Amendment, Mulch Rings, Punch-List | C9: =Planting!N48 -> 124759.05 | D9: UP + RP + Live Stakes + localized soil/mulch only
A10: 2 | B10: Commercial Carry – Scaled to Limited Scope | C10: =Commercial!I21 -> 46000 | D10: Mob, foreman, cert payroll, submittals, closeout, insurance/bond
A11: 3 | B11: Plant Establishment / Maintenance (Yr 1 + Yr 2 in base bid) | C11: =Establishment!O28 -> 39740 | D11: Yr 3 = AA-03 (not in base bid)
A12: 4 | B12: Irrigation / Temporary Watering | C12: 0 | D12: EXCLUDED – RFI-01 CLOSED. Priced as AA-04 if formally directed in writing.
A13: TOTAL RAW PROJECTED COST | C13: =SUM(C9:C12) -> 210499.05 | D13: Sum of all base bid divisions (before markup)
A15: ── MARKUP / PRICING OPTIONS ──
A16: 0.05 | B16: Contingency (5% of Raw Cost) | C16: =C13*A16 -> 10524.952 | D16: Applied before profit markup
B17: SUBTOTAL BEFORE PROFIT MARKUP | C17: =C13+C16 -> 221024
A18: 0.2 | B18: OPTION A – 20% MARKUP on Cost | C18: =C17*A18 -> 44204.801 | D18: 16.7% Gross Profit Margin
B19: OPTION A – TOTAL BID (20% Markup) | C19: =C17+C18 -> 265228.8
A20: 0.25 | B20: OPTION B – 25% MARKUP on Cost ← 20% GP MARGIN TARGET | C20: =C17*A20 -> 55256.001 | D20: 20% Gross Profit Margin – RECOMMENDED (Gold Standard target)
B21: OPTION B – TOTAL BID (20% GP Margin) ← RECOMMENDED | C21: =C17+C20 -> 276280 | D21: ← Gold Standard target gross profit
A23: ADD-ALTERNATES (NOT IN BASE BID – Price separately after applying same 5% contingency + 25% markup)
A24: AA-01 | B24: CAVFS Only (2.66 AC) | C24: ='Add-Alternates'!N13 -> 134409.2 | D24: Raw cost – apply 5% contingency + 25% markup for bid price
A25: AA-02 | B25: CABS / Bioretention Limited Interface | C25: ='Add-Alternates'!N20 -> 156368.43 | D25: Raw cost – apply 5% contingency + 25% markup for bid price
A26: AA-03 | B26: Year 3 Plant Establishment | C26: ='Add-Alternates'!N24 -> 6000 | D26: Raw cost – apply 5% contingency + 25% markup for bid price
A27: AA-04 | B27: Temporary Watering (if formally directed) | C27: ='Add-Alternates'!N31 -> 26497 | D27: Raw cost – apply 5% contingency + 25% markup for bid price
A28: TOTAL ALL ADD-ALTERNATES (raw cost if all accepted) | C28: ='Add-Alternates'!N38 -> 323274.63
A30: ✅ DOCUMENT BASIS | C30: Rev-04 Basis: Full WSDOT Archive – Plans Vol. 1-4 + Specs Vol. 1-2 + Addenda + Q&A. Quantities confirmed from LSN01 (Sheet 275/635). Rev-04 limited scope per Nathan Petty instructions dated June 2026.
A31: SUBMISSION STATUS | C31: NEAR SUBMISSION-READY – Rev-04 Limited Scope. Scope reduced per Gold Standard bonding/risk decision. Add-Alternates AA-01 to AA-04 available upon Gold Standard direction. Date corrected to June 2026.
A32: ⚠ INSURANCE / BOND | C32: GL Insurance ($4,500) and Bond ($5,000) already in Commercial tab scaled to this package. Do NOT add insurance % again in markup – this would double-count.
A33: ⛔ EXCLUDED (BASE BID) | C33: Hydroseeding, full-site seeding, full-site bark mulch, fine grading, topsoil stripping, CAVFS/MVFS, CABS, bioretention, underdrain, check dams, irrigation, traffic control, civil earthwork, TESC beyond GS work area.
A35: 📌 BID RANGE NOTE: Base Bid alone (Option B) = ~$274K, which is BELOW Nathan's $300K floor on its own. The $300K–$500K target is met for the overall submitted package only when at least one Add-Alternate is included: Base Bid + AA-01 (CAVFS) = ~$450K (within range). Base Bid + AA-01 + AA-02 = ~$656K (exceeds range). Gold Standard must select AA-01 at minimum to land in the requested range, or confirm a base-bid-only submission is acceptable.
