Workbook

Sheet Summary
B2: SUMMARY
B14: DATE | D14: PROJECT NAME | E14: ='Detailed Estimate Sheet'!J15 -> PROJECT LOCATION
B15: ='Detailed Estimate Sheet'!B16 -> 45708 | D15: ='Detailed Estimate Sheet'!D16 -> Building E Roof Replacement For UPMC Altoona | E15: ='Detailed Estimate Sheet'!J16 -> 0
D16: ='Detailed Estimate Sheet'!D17 -> 0
B18: LINE NO. | C18: CSI DIV. | D18: DESCRIPTION | E18: MATERIAL COST | F18: LABOR COST | G18: TOTAL COST
B20: =IF(G20<>"",1+MAX($B$18:B19),"") -> 1 | C20: ='Detailed Estimate Sheet'!C21 -> DIV. 01 | D20: ='Detailed Estimate Sheet'!D21 -> GENERAL REQUIREMENTS | E20: ='Detailed Estimate Sheet'!H21+('Detailed Estimate Sheet'!H21*('Detailed Estimate Sheet'!$Q$8+'Detailed Estimate Sheet'!$Q$10+'Detailed Estimate Sheet'!$Q$12))+('Detailed Estimate Sheet'!$Q$11*('Detailed Estimate Sheet'!H21+'Detailed Estimate Sheet'!H21*'Detailed Estimate Sheet'!$Q$8+'Detailed Estimate Sheet'!H21*'Detailed Estimate Sheet'!$Q$10)) -> 0 | F20: ='Detailed Estimate Sheet'!O21+('Detailed Estimate Sheet'!O21*('Detailed Estimate Sheet'!$Q$9+'Detailed Estimate Sheet'!$Q$10+'Detailed Estimate Sheet'!$Q$12))+('Detailed Estimate Sheet'!$Q$11*('Detailed Estimate Sheet'!O21+'Detailed Estimate Sheet'!O21*'Detailed Estimate Sheet'!$Q$9+'Detailed Estimate Sheet'!O21*'Detailed Estimate Sheet'!$Q$10)) -> 0 | G20: ='Detailed Estimate Sheet'!R21 -> 0
B21: =IF(G21<>"",1+MAX($B$18:B20),"") -> 2 | C21: ='Detailed Estimate Sheet'!C25 -> DIV. 02 | D21: ='Detailed Estimate Sheet'!D25 -> EXISTING CONDITIONS | E21: ='Detailed Estimate Sheet'!H25+('Detailed Estimate Sheet'!H25*('Detailed Estimate Sheet'!$Q$8+'Detailed Estimate Sheet'!$Q$10+'Detailed Estimate Sheet'!$Q$12))+('Detailed Estimate Sheet'!$Q$11*('Detailed Estimate Sheet'!H25+'Detailed Estimate Sheet'!H25*'Detailed Estimate Sheet'!$Q$8+'Detailed Estimate Sheet'!H25*'Detailed Estimate Sheet'!$Q$10)) -> 0 | F21: ='Detailed Estimate Sheet'!O25+('Detailed Estimate Sheet'!O25*('Detailed Estimate Sheet'!$Q$9+'Detailed Estimate Sheet'!$Q$10+'Detailed Estimate Sheet'!$Q$12))+('Detailed Estimate Sheet'!$Q$11*('Detailed Estimate Sheet'!O25+'Detailed Estimate Sheet'!O25*'Detailed Estimate Sheet'!$Q$9+'Detailed Estimate Sheet'!O25*'Detailed Estimate Sheet'!$Q$10)) -> 0 | G21: ='Detailed Estimate Sheet'!R25 -> 0
B22: =IF(G22<>"",1+MAX($B$18:B21),"") -> 3 | C22: ='Detailed Estimate Sheet'!C41 -> DIV. 07 | D22: ='Detailed Estimate Sheet'!D41 -> THERMAL AND MOISTURE PROTECTION | E22: ='Detailed Estimate Sheet'!H41+('Detailed Estimate Sheet'!H41*('Detailed Estimate Sheet'!$Q$8+'Detailed Estimate Sheet'!$Q$10+'Detailed Estimate Sheet'!$Q$12))+('Detailed Estimate Sheet'!$Q$11*('Detailed Estimate Sheet'!H41+'Detailed Estimate Sheet'!H41*'Detailed Estimate Sheet'!$Q$8+'Detailed Estimate Sheet'!H41*'Detailed Estimate Sheet'!$Q$10)) -> 0 | F22: ='Detailed Estimate Sheet'!O41+('Detailed Estimate Sheet'!O41*('Detailed Estimate Sheet'!$Q$9+'Detailed Estimate Sheet'!$Q$10+'Detailed Estimate Sheet'!$Q$12))+('Detailed Estimate Sheet'!$Q$11*('Detailed Estimate Sheet'!O41+'Detailed Estimate Sheet'!O41*'Detailed Estimate Sheet'!$Q$9+'Detailed Estimate Sheet'!O41*'Detailed Estimate Sheet'!$Q$10)) -> 0 | G22: ='Detailed Estimate Sheet'!R41 -> 0
B24: 12 | D24: TOTAL PROJECT COST | G24: =SUM(G20:G23) -> 0

Sheet Detailed Estimate Sheet
T1: MAT. FAC. | U1: LAB. FAC.
B2: CONSTRUCTION COST ESTIMATE BREAKDOWN | T2: 1 | U2: 1
B3: CONTRACTOR | I3: ADDRESS | T3: 1.016 | U3: 1.773
I5: TOTAL MATERIAL COST | R5: =SUM(I22:I67) -> 0
I6: TOTAL LABOR COST | R6: =SUM(P22:P67) -> 0
I7: SUBTOTAL | R7: =SUM(R5:R6) -> 0
I8: SALES TAX | Q8: 0.08875 | R8: =R5*Q8 -> 0
I9: LABOR BURDEN | Q9: 0.22 | R9: =R6*Q9 -> 0
I10: OVERHEAD & PROFIT | Q10: 0.25 | R10: =R7*Q10 -> 0
I11: BONDING | Q11: 0.02 | R11: =SUM(R7:R10)*Q11 -> 0
I12: CONTINGENCY / WASTAGE | Q12: 0.05 | R12: =R7*Q12 -> 0
I13: PROPOSED PROJECT AMOUNT | R13: =SUM(R7:R12) -> 0
I14: TOTAL MANHOURS | R14: =SUM(K22:K67) -> 0
B15: DATE | D15: PROJECT NAME | E15: SCOPE OF WORK | J15: PROJECT LOCATION
B16: =TODAY() -> 45708 | D16: Building E Roof Replacement For UPMC Altoona | E16: Roof Replacement
B18: LINE NO. | C18: DWG REF./ CSI SEC. | E18: UNIT OF MEASURE | F18: QUANTITY | G18: MATERIAL | J18: LABOR | Q18: LINE TOTAL | R18: TRADE TOTAL W/ S.TAX, O&P
G19: UNIT PRICE | H19: UNIT PRICE | I19: TOTAL COST | J19: UNIT LABOR HOUR | K19: LABOR HOURS | L19: CREW | M19: LABOR RATE | N19: LABOR RATE | O19: UNIT PRICE | P19: TOTAL COST
B20: =IF(F20<>"",1+MAX($B$1:B19),"")
B21: =IF(F21<>"",1+MAX($B$1:B20),"") | C21: DIV. 01 | D21: GENERAL REQUIREMENTS | E21: SUBTOTAL MATERIAL | H21: =SUM(I22:I24) -> 0 | I21: =F21*H21 -> 0 | K21: SUBTOTAL LABOR | O21: =SUM(P22:P24) -> 0 | P21: =F21*O21 -> 0 | Q21: =SUM(Q22:Q24) -> 0 | R21: =(Q21)+(H21*$Q$8)+(O21*$Q$9)+(Q21*$Q$10)+($Q$11*((Q21)+(H21*$Q$8)+(O21*$Q$9)+(Q21*$Q$10)))+(Q21*$Q$12) -> 0
H22: =G22*$T$2 -> 0 | I22: =F22*H22 -> 0 | K22: =F22*J22 -> 0 | N22: =M22*$U$2 -> 0 | O22: =J22*N22 -> 0 | P22: =F22*O22 -> 0 | Q22: =I22+P22 -> 0
B23: =IF(F23<>"",1+MAX($B$22:B22),"") -> 1 | D23: PERMITS, SITE SUPERVISION, FINAL CLEANUP & DUMPSTER | E23: LS | F23: 1 | H23: =G23*$T$2 -> 0 | I23: =F23*H23 -> 0 | K23: =F23*J23 -> 0 | N23: =M23*$U$2 -> 0 | O23: 0 | P23: =F23*O23 -> 0
B24: =IF(F24<>"",1+MAX($B$22:B23),"") | H24: =G24*$T$2 -> 0 | I24: =F24*H24 -> 0 | K24: =F24*J24 -> 0 | N24: =M24*$U$2 -> 0 | O24: =J24*N24 -> 0 | P24: =F24*O24 -> 0 | Q24: =I24+P24 -> 0
B25: =IF(F25<>"",1+MAX($B$22:B24),"") | C25: DIV. 02 | D25: EXISTING CONDITIONS | E25: SUBTOTAL MATERIAL | H25: =SUM(I26:I36) -> 0 | I25: =F25*H25 -> 0 | K25: SUBTOTAL LABOR | O25: =SUM(P26:P39) -> 0 | P25: =F25*O25 -> 0 | Q25: =SUM(Q26:Q39) -> 0 | R25: =(Q25)+(H25*$Q$8)+(O25*$Q$9)+(Q25*$Q$10)+($Q$11*((Q25)+(H25*$Q$8)+(O25*$Q$9)+(Q25*$Q$10)))+(Q25*$Q$12) -> 0
B26: =IF(F26<>"",1+MAX($B$22:B25),"") | H26: =G26*$T$2 -> 0 | I26: =F26*H26 -> 0 | K26: =F26*J26 -> 0 | N26: =M26*$U$2 -> 0 | O26: =J26*N26 -> 0 | P26: =F26*O26 -> 0 | Q26: =I26+P26 -> 0
B27: =IF(F27<>"",1+MAX($B$22:B26),"") | D27: DEMOLITION | H27: =G27*$T$2 -> 0 | I27: =F27*H27 -> 0 | K27: =F27*J27 -> 0 | N27: =M27*$U$2 -> 0 | O27: =J27*N27 -> 0 | P27: =F27*O27 -> 0 | Q27: =I27+P27 -> 0
B28: =IF(F28<>"",1+MAX($B$22:B27),"") -> 2 | C28: AD101 | D28: Existing Sloped Zonolite 'Crickets' Shall Be Completely Removed Down To The Tectum Deck | E28: SF | F28: 3795 | H28: =G28*$T$2 -> 0 | I28: =F28*H28 -> 0 | J28: 0 | K28: =F28*J28 -> 0 | L28: 1 CLAB | M28: 42.1 | N28: 0 | O28: =J28*N28 -> 0 | P28: =F28*O28 -> 0 | Q28: =I28+P28 -> 0
B29: =IF(F29<>"",1+MAX($B$22:B28),"") -> 3 | D29: Existing Tectum Deck Shall Be Swept/Blown Clean Of All Dirt, Water & Debris | E29: SF | F29: 11725 | H29: =G29*$T$2 -> 0 | I29: =F29*H29 -> 0 | J29: 0 | K29: =F29*J29 -> 0 | L29: 1 CLAB | M29: 42.1 | N29: 0 | O29: =J29*N29 -> 0 | P29: =F29*O29 -> 0 | Q29: =I29+P29 -> 0
B30: =IF(F30<>"",1+MAX($B$22:B29),"") -> 4 | D30: Existing Wood Platform & Railings To Be Remove, Salvage & Reinsatll | E30: SF | F30: 65 | H30: =G30*$T$2 -> 0 | I30: =F30*H30 -> 0 | J30: 0 | K30: =F30*J30 -> 0 | L30: 1 CLAB | M30: 42.1 | N30: 0 | O30: =J30*N30 -> 0 | P30: =F30*O30 -> 0 | Q30: =I30+P30 -> 0
B31: =IF(F31<>"",1+MAX($B$22:B30),"") -> 5 | D31: Existing Roof Pavers To Be Remove, Salvage & Reinsatll | E31: SF | F31: 310 | H31: =G31*$T$2 -> 0 | I31: =F31*H31 -> 0 | J31: 0 | K31: =F31*J31 -> 0 | L31: 1 CLAB | M31: 42.1 | N31: 0 | O31: =J31*N31 -> 0 | P31: =F31*O31 -> 0 | Q31: =I31+P31 -> 0
D32: Existing Wood Stairs & Railings To Be Removed | E32: SF | F32: 14 | H32: =G32*$T$2 -> 0 | I32: =F32*H32 -> 0 | J32: 0 | K32: =F32*J32 -> 0 | L32: 1 CLAB | M32: 42.1 | N32: 0 | O32: =J32*N32 -> 0 | P32: =F32*O32 -> 0 | Q32: =I32+P32 -> 0
D33: Existing Roofing Materials To Be Removed | E33: SF | F33: 11725 | H33: =G33*$T$2 -> 0 | I33: =F33*H33 -> 0 | J33: 0 | K33: =F33*J33 -> 0 | L33: 1 CLAB | M33: 42.1 | N33: 0 | O33: =J33*N33 -> 0 | P33: =F33*O33 -> 0 | Q33: =I33+P33 -> 0
D34: Existing Stair To Be Remove & Dispose | E34: SF | F34: 17 | H34: =G34*$T$2 -> 0 | I34: =F34*H34 -> 0 | J34: 0 | K34: =F34*J34 -> 0 | L34: 1 CLAB | M34: 42.1 | N34: 0 | O34: =J34*N34 -> 0 | P34: =F34*O34 -> 0 | Q34: =I34+P34 -> 0
D35: Unfasten & lift Exsiting Low-Profile Exhaust To Allow For Removal Of Existing Roofing System & Installation Of New Roofing System. Reinstall & Fasten Exhaust (Review & coordinate w/ Owner) | E35: EA | F35: 15 | H35: =G35*$T$2 -> 0 | I35: =F35*H35 -> 0 | J35: 0 | K35: =F35*J35 -> 0 | L35: 1 CLAB | M35: 42.1 | N35: 0 | O35: =J35*N35 -> 0 | P35: =F35*O35 -> 0 | Q35: =I35+P35 -> 0
D36: Existing Fascia To Be Removed | E36: LF | F36: 527 | H36: =G36*$T$2 -> 0 | I36: =F36*H36 -> 0 | J36: 0 | K36: =F36*J36 -> 0 | L36: 1 CLAB | M36: 42.1 | N36: 0 | O36: =J36*N36 -> 0 | P36: =F36*O36 -> 0 | Q36: =I36+P36 -> 0
D38: Patch & Repair
C39: AD101 | D39: Patch & Repair Fireproofing & Rated Assemblies Damaged During Demolition | E39: SF | F39: 11725
B40: =IF(F40<>"",1+MAX($B$22:B36),"") | H40: =G40*$T$2 -> 0 | I40: =F40*H40 -> 0 | K40: =F40*J40 -> 0 | N40: =M40*$U$2 -> 0 | O40: =J40*N40 -> 0 | P40: =F40*O40 -> 0 | Q40: =I40+P40 -> 0
B41: =IF(F41<>"",1+MAX($B$22:B40),"") | C41: DIV. 07 | D41: THERMAL AND MOISTURE PROTECTION | E41: SUBTOTAL MATERIAL | H41: =SUM(I42:I66) -> 0 | I41: =F41*H41 -> 0 | K41: SUBTOTAL LABOR | O41: =SUM(P42:P66) -> 0 | P41: =F41*O41 -> 0 | Q41: =SUM(Q42:Q65) -> 0 | R41: =(Q41)+(H41*$Q$8)+(O41*$Q$9)+(Q41*$Q$10)+($Q$11*((Q41)+(H41*$Q$8)+(O41*$Q$9)+(Q41*$Q$10)))+(Q41*$Q$12) -> 0
B42: =IF(F42<>"",1+MAX($B$22:B41),"") | D42: Roofing | H42: =G42*$T$2 -> 0 | I42: =F42*H42 -> 0 | K42: =F42*J42 -> 0 | N42: =M42*$U$2 -> 0 | O42: =J42*N42 -> 0 | P42: =F42*O42 -> 0 | Q42: =I42+P42 -> 0
B43: =IF(F43<>"",1+MAX($B$22:B42),"") -> 6 | C43: A101 | D43: New Fully-Adhered Non-Reinforced Black EPDM Rubber Membrane Roofing | E43: SF | F43: 11723 | H43: 0 | I43: =F43*H43 -> 0 | J43: 0 | K43: 0 | L43: B-2 | M43: 42.5 | N43: 0 | O43: =J43*N43 -> 0 | P43: =F43*O43 -> 0 | Q43: =I43+P43 -> 0
B44: =IF(F44<>"",1+MAX($B$22:B43),"") -> 7 | D44: Cricket Roof | E44: SF | F44: 2186 | G44: 2.46 | H44: 0 | I44: =F44*H44 -> 0 | J44: 0 | K44: 0 | L44: B-2 | M44: 42.5 | N44: 0 | O44: =J44*N44 -> 0 | P44: =F44*O44 -> 0 | Q44: =I44+P44 -> 0
B45: =IF(F45<>"",1+MAX($B$22:B44),"") | H45: =G45*$T$2 -> 0 | I45: =F45*H45 -> 0 | K45: =F45*J45 -> 0 | N45: =M45*$U$2 -> 0 | O45: =J45*N45 -> 0 | P45: =F45*O45 -> 0 | Q45: =I45+P45 -> 0
B46: =IF(F46<>"",1+MAX($B$22:B45),"") | D46: Insulation | H46: =G46*$T$2 -> 0 | I46: =F46*H46 -> 0 | K46: =F46*J46 -> 0 | N46: =M46*$U$2 -> 0 | O46: =J46*N46 -> 0 | P46: =F46*O46 -> 0 | Q46: =I46+P46 -> 0
B47: =IF(F47<>"",1+MAX($B$22:B46),"") -> 8 | C47: A101 | D47: Furnish & Install Two (2) New Layers Of 2.6" Thick Flat "Securhield" Polyiso Insulation (25 Psi Compressive Strength) @ Roofing | E47: SF | F47: 11723 | G47: 2.46 | H47: 0 | I47: =F47*H47 -> 0 | J47: 0 | K47: 0 | L47: B-2 | M47: 42.5 | N47: 0 | O47: =J47*N47 -> 0 | P47: =F47*O47 -> 0 | Q47: =I47+P47 -> 0
B48: =IF(F48<>"",1+MAX($B$22:B47),"") -> 9 | D48: Furnish & Install 18"Wide 1/2" Per Foot Tepered "Securshield" Polysio Insulation @ Cricket Roof | E48: SF | F48: 75 | G48: 3.78 | H48: 0 | I48: =F48*H48 -> 0 | J48: 0 | K48: 0 | L48: B-2 | M48: 42.5 | N48: 0 | O48: =J48*N48 -> 0 | P48: =F48*O48 -> 0 | Q48: =I48+P48 -> 0
B49: =IF(F49<>"",1+MAX($B$22:B48),"") -> 10 | D49: Furnish & Install 1/2" Per Foot Tepered "Securshield" Polysio Insulation @ Cricket Roof | E49: SF | F49: 2111 | G49: 3.78 | H49: 0 | I49: =F49*H49 -> 0 | J49: 0 | K49: 0 | L49: B-2 | M49: 42.5 | N49: 0 | O49: =J49*N49 -> 0 | P49: =F49*O49 -> 0 | Q49: =I49+P49 -> 0
B50: =IF(F50<>"",1+MAX($B$22:B49),"") | H50: =G50*$T$2 -> 0 | I50: =F50*H50 -> 0 | K50: =F50*J50 -> 0 | N50: =M50*$U$2 -> 0 | O50: =J50*N50 -> 0 | P50: =F50*O50 -> 0 | Q50: =I50+P50 -> 0
B51: =IF(F51<>"",1+MAX($B$22:B50),"") | D51: FLASHING | H51: =G51*$T$2 -> 0 | I51: =F51*H51 -> 0 | K51: =F51*J51 -> 0 | N51: =M51*$U$2 -> 0 | O51: =J51*N51 -> 0 | P51: =F51*O51 -> 0 | Q51: =I51+P51 -> 0
B52: =IF(F52<>"",1+MAX($B$22:B51),"") -> 11 | C52: A101 | D52: Kynar 500 Finish Aluminium Ledge Flashing Including Internal Splice Plates & Continuous 24 GA Galvanized Cleat | E52: LF | F52: 497 | G52: 2.02 | H52: 0 | I52: =F52*H52 -> 0 | J52: 0 | K52: 0 | L52: B-2 | M52: 42.5 | N52: 0 | O52: =J52*N52 -> 0 | P52: =F52*O52 -> 0 | Q52: =I52+P52 -> 0
B53: =IF(F53<>"",1+MAX($B$22:B52),"") -> 12 | D53: Furnish & Install New Kynar 500 Finish Aluminium Surface Mounted Counter Flashing | E53: LF | F53: 129 | G53: 1.02 | H53: 0 | I53: =F53*H53 -> 0 | J53: 0 | K53: 0 | L53: B-2 | M53: 42.5 | N53: 0 | O53: =J53*N53 -> 0 | P53: =F53*O53 -> 0 | Q53: =I53+P53 -> 0
B54: =IF(F54<>"",1+MAX($B$22:B53),"") -> 13 | D54: Stainless Steel Counter Flashing | E54: LF | F54: 80 | G54: 2.02 | H54: 0 | I54: =F54*H54 -> 0 | J54: 0 | K54: 0 | L54: B-2 | M54: 42.5 | N54: 0 | O54: =J54*N54 -> 0 | P54: =F54*O54 -> 0 | Q54: =I54+P54 -> 0
D56: Stair
C57: A101 | D57: (11"Tread & 7"Riser @ 2'-9"W) New Treated Wood Step | E57: EA | F57: 5 | H57: 0 | I57: =F57*H57 -> 0 | J57: 0 | K57: 0 | L57: B-2 | M57: 42.5 | N57: 0 | O57: =J57*N57 -> 0 | P57: =F57*O57 -> 0 | Q57: =I57+P57 -> 0
B58: =IF(F58<>"",1+MAX($B$22:B54),"") -> 14 | D58: Stair Railing | E58: LF | F58: 9 | G58: 1.02 | H58: 0 | I58: =F58*H58 -> 0 | J58: 0 | K58: 0 | L58: B-2 | M58: 42.5 | N58: 0 | O58: =J58*N58 -> 0 | P58: =F58*O58 -> 0 | Q58: =I58+P58 -> 0
B59: =IF(F59<>"",1+MAX($B$22:B58),"") -> 15 | D59: Stringer | E59: LF | F59: 7 | G59: 1.02 | H59: 0 | I59: =F59*H59 -> 0 | J59: 0 | K59: 0 | L59: B-2 | M59: 42.5 | N59: 0 | O59: =J59*N59 -> 0 | P59: =F59*O59 -> 0 | Q59: =I59+P59 -> 0
B60: =IF(F60<>"",1+MAX($B$22:B59),"") | H60: =G60*$T$2 -> 0 | I60: =F60*H60 -> 0 | K60: =F60*J60 -> 0 | N60: =M60*$U$2 -> 0 | O60: =J60*N60 -> 0 | P60: =F60*O60 -> 0 | Q60: =I60+P60 -> 0
B61: =IF(F61<>"",1+MAX($B$22:B60),"") | D61: Other | H61: =G61*$T$2 -> 0 | I61: =F61*H61 -> 0 | K61: =F61*J61 -> 0 | N61: =M61*$U$2 -> 0 | O61: =J61*N61 -> 0 | P61: =F61*O61 -> 0 | Q61: =I61+P61 -> 0
C62: A101 | D62: Furnish & Install New Concrete Pavers | E62: SF | F62: 350 | H62: 0 | I62: =F62*H62 -> 0 | J62: 0 | K62: 0 | L62: B-2 | M62: 42.5 | N62: 0 | O62: =J62*N62 -> 0 | P62: =F62*O62 -> 0 | Q62: =I62+P62 -> 0
D63: Manufactured Keynar 500 Finish Aluminium 2-Piece "Snap-Lock" Securedge 300 Roof Edge (Color By Architect) - Install Complete w/ Internal Splice Plates & Gap 1/4" For Expansion | E63: LF | F63: 497 | H63: 0 | I63: =F63*H63 -> 0 | J63: 0 | K63: 0 | L63: B-2 | M63: 42.5 | N63: 0 | O63: =J63*N63 -> 0 | P63: =F63*O63 -> 0 | Q63: =I63+P63 -> 0
D64: Apply A Cont. Bed Of Water Cut-Off Mastic Behind The Membrane | E64: LF | F64: 129 | H64: 0 | I64: =F64*H64 -> 0 | J64: 0 | K64: 0 | L64: B-2 | M64: 42.5 | N64: 0 | O64: =J64*N64 -> 0 | P64: =F64*O64 -> 0 | Q64: =I64+P64 -> 0
D65: Fascia Into 6" Wood Blocking | E65: LF | F65: 497 | H65: 0 | I65: =F65*H65 -> 0 | J65: 0 | K65: 0 | L65: B-2 | M65: 42.5 | N65: 0 | O65: =J65*N65 -> 0 | P65: =F65*O65 -> 0 | Q65: =I65+P65 -> 0
B67: =IF(F67<>"",1+MAX($B$22:B66),"") | H67: =G67*$T$2 -> 0 | I67: =F67*H67 -> 0 | K67: =F67*J67 -> 0 | N67: =M67*$U$2 -> 0 | O67: =J67*N67 -> 0 | P67: =F67*O67 -> 0 | Q67: =I67+P67 -> 0
